solar_functions/solar/__init__.py
solar_functions/solar/__solardate__/__init__.py
solar_functions/solar/__solardate__/jalali.py
solar_functions-1.0.5.dist-info/WHEEL
solar_functions-1.0.5.dist-info/METADATA
solar_functions-1.0.5.dist-info/RECORD
