Metadata-Version: 2.1
Name: solar-functions
Version: 1.0.5
Summary: solar-functions This Module is Designed With Love For Iranian Developers And Programmers By Sami Dev | Telegram: T.me/Sami_Dev
Author: Sami Dev
Author-email: hzsami82@email.com
Requires-Python: >=3.7,<4.0
Classifier: Programming Language :: Python :: 3
Classifier: Programming Language :: Python :: 3.10
Classifier: Programming Language :: Python :: 3.7
Classifier: Programming Language :: Python :: 3.8
Classifier: Programming Language :: Python :: 3.9
